[
	{
		"name": "Free Cites",
		"leaderName": "Basil Horov",
		"personality": "Survivalist",
		"adjective": ["alien"],
		"startBias": ["Badlands"],
		"preferredVictoryType": "Diplomatic",
		
		"startIntroPart1": "We saw bombs falling to the ground and destroying everything behind them, everything that could be destroyed, but it did not destroy us. We are alive and we are ready to restore what was destroyed.",
		"startIntroPart2": "Use your diplomatic capabilities to expand your influence and achieve a diplomatic victory!",
		
		"declaringWar": "It's time to free your Cities from corporate shackles",
		"attacked": "Do you think you can crush our common people? No one will ever be able to do this, including you.",
		"defeated": "How is it possible that those Apes hurt us? The galactic senate will take care of them.",
		"introduction": "As superior galactic entities, you are not worthy of our attention.",
		
		"neutralHello": "Welcome",
		"neutralLetsHearIt": ["Go on.","What do you say?","You may begin."],
		"neutralNo": ["We absolutely refuse.","No!","I refuse."],
		"neutralYes": ["Very good.","Of course, yes.","That is very good."],

		"hateHello": "Be careful in your actions. We have known your evil nature for a long time.",
		"hateLetsHearIt": ["Speak!","What do you say?","Go on."],
		"hateNo": ["That is not possible!","We are not agreeing to that!","I beg your pardon?"],
		"hateYes": ["That is fine.","That is good enough.","Very well..."],
		
		"afterPeace": "Let's stop this bloodshed for the sake of our peoples.",
		"tradeRequest": "Let's bargain. It will be good for both of us.",

		"outerColor": [16,16,16],
		"innerColor": [255,200,200],
		"uniqueName": "Unity",
		"uniques": [
			"[+15]% Great Person generation [in all cities]",
			"Starts with [Secrets of the Past]",
			"City-State territory always counts as friendly territory",
			"Starts with [Expansionism] adopted",
			"City-State Influence recovers at twice the normal rate"
		],
		"cities": ["Troeholmsk","Hatki","Kornadi","Svetorechino","Nowyy Brest","Mirsky zamok","Minsky trackt","Vigonochanskoe","Baranowichi"]
	}
]
