[
	/*

	Here is a template to show what values should be filled in. 
	Use the description at http://civdata.com/, and adjust the numbers accordingly.
	Even then, its up to personal interpretation.
	To generate lines with multiple parameters I used the function: (FirstParam + (SecondParam - 5) / 2).

	{
		"name": "Template",
		// Stats focused personalities
		"culture": Culture,
		"faith": Religion,
		"food": Growth,
		"gold": Gold,
		"happiness": Happiness,
		"production": Production,
		"science": Science,
		// Behavour focused personalities
		"military": Military Training,
		"aggressive": Offensive or (10 - defensive) which ever is higher,
		"declareWar": War,
		"commerce": Gold + Chattiness,
		"diplomacy": Diplomatic Balance + Friendly,
		"loyal": Loyalty + Defense,
		"expansion": Expansion,

		"priorities": {
			"Adaptation": Growth + Culture + Defensive,
			"Expansionism": Expansion + CityStateCompetitiveness + CSFriendly,
			"Sovereignty": Boldness + War,
			"Theocracy": Religion + War,
			"Rationalism": Science + Terraformer,
			"Constitution": Growth + Culture + Happiness,
			"Supremacy": Boldness + War,
			"Monopoly": Gold + Chattiness + CityStateCompetitiveness + CSFriendly,
			"Collectivism": Defensive + Production,
			"Naturalism": Growth + Culture + Happiness,
			"Mechanization": Boldness + Production + Military training,
			"Bionics": Boldness + Science + Military training + Terraformer
		},
		"civilopediaText": [
			{"text": "."}
		]
	},
*/

	{
		"name": "Keiji",
		"production": 5,
		"food": 5,
		"gold": 7,
		"science": 6,
		"culture": 5,
		"happiness": 8,
		"faith": 5,
		"military": 7,
		"aggressive": 3,
		"declareWar": 3,
		"commerce": 7,
		"diplomacy": 7,
		"loyal": 7,
		"expansion": 5,
		"priorities": {
			"Adaptation": 10,
			"Expansionism": 30,
			"Sovereignty": 20,
			"Theocracy": 10,
			"Rationalism": 30,
			"Constitution": 20,
			"Supremacy": 0,
			"Monopoly": 30,
			"Collectivism": 0,
			"Naturalism": 0,
			"Mechanization": 0,
			"Bionics": 40
		}
]
