[
	{
		"name": "Opolchenets",
		"unitType": "Scrapper",
		"uniqueTo": "Free Cites",
		"replaces": "Spearman",
		"movement": 2,
		"strength": 17,
		"cost": 50,
		"obsoleteTech": "Rifling",
		"upgradesTo": "Militia",
		"uniques": [
			"Low Tech",
			"[+50]% Strength <vs [Mounted] units>",
			"Excess Food converted to Production when under construction"
		],
		"attackSound": "metalhit"
	},
	{
		"name": "Druzina",
		"unitType": "Scrapper",
		"uniqueTo": "The Harbingers",
		"replaces": "Militia",
		"movement": 2,
		"strength": 36,
		"interceptRange": 1,
		"cost": 65,
		"requiredTech": "The Wheel",
		"obsoleteTech": "Replaceable Parts",
		"upgradesTo": "Soldier",
		"hurryCostModifier": -20,
		"uniques": ["Personnel"],
		"promotions": ["Entrench"],
		"attackSound": "machinegun"
	},
]
